goodstats/__init__.py
goodstats/_model_wls.py
goodstats/_utils.py
goodstats-0.0.3.dist-info/METADATA
goodstats-0.0.3.dist-info/WHEEL
goodstats-0.0.3.dist-info/licenses/LICENSE
goodstats-0.0.3.dist-info/RECORD
