Metadata-Version: 2.3
Name: goodstats
Version: 0.0.3
Summary: Statistics models and tests that return 'tidy' classes
Project-URL: Homepage, https://github.com/sodium-hydroxide/goodstats
Project-URL: Repository, https://github.com/sodium-hydroxide/goodstats.git
Author-email: Noah Blair <noahjblair@outlook.com>
Maintainer-email: Noah Blair <noahjblair@outlook.com>
License:                     GNU GENERAL PUBLIC LICENSE
License-File: LICENSE
Keywords: regression,statistics
Requires-Python: >=3.10
Requires-Dist: matplotlib
Requires-Dist: numpy
Requires-Dist: pandas
Requires-Dist: patsy
Requires-Dist: scipy
Requires-Dist: statsmodels
